shellboard/Core.py
shellboard/Menu.py
shellboard/Widgets.py
shellboard/__init__.py
shellboard-0.4.0.1a2.dist-info/LICENSE
shellboard-0.4.0.1a2.dist-info/METADATA
shellboard-0.4.0.1a2.dist-info/WHEEL
shellboard-0.4.0.1a2.dist-info/top_level.txt
shellboard-0.4.0.1a2.dist-info/RECORD
